{
  "items": [
    {
      "id": "share-our-first-post-on-substack",
      "name": "Share our first post on Substack!",
      "subtitle": "Write our first post on Substack - introduce ourselves and a bit about Project Runecraft",
      "location": "done",
      "region": "General",
      "category": "other",
      "progress": 100,
      "fanRequest": false,
      "estimatedTotalTime": 1,
      "estimatedTimeLeft": "0 hours",
      "what": "Our first article is now live! Check it out!\n\nQuest complete!",
      "images": [
        {
          "src": "assets/uploads/1777458004489-composed.jpg",
          "caption": "Our article"
        }
      ]
    },
    {
      "id": "wizard-s-tower",
      "name": "Wizard's Tower",
      "subtitle": "Our first building! Testing out WorldEdit on the Wizard's Tower near Draynor. Trialling a landscaping - foundation planning - walls and exterior - roof exterior - decorating exterior - designing interior - designing underground - placing lighting - finishing homely touches. Includes the connecting bridge with the STASH",
      "location": "progress",
      "region": "Misthalin",
      "category": "building",
      "progress": 55,
      "fanRequest": false,
      "estimatedTotalTime": 10,
      "estimatedTimeLeft": "4 hours 30 minutes",
      "what": "28/04 - Check out the pretty pictures! Landscaping, foundations, walls, exterior, roof and environment completed. Cycled through a couple of techniques and building materials for this. We now have some decent stencils (trees, walls, bricks, roads) we can copy to new buildings :)\n\nNext step - interior!",
      "images": [
        {
          "src": "assets/uploads/1777415094992-exterior-wizards-tower-1.jpg",
          "caption": "exterior - north east"
        },
        {
          "src": "assets/uploads/1777415087990-exterior-wizards-tower-5.jpg",
          "caption": "exterior - south east"
        },
        {
          "src": "assets/uploads/1777415089285-exterior-wizards-tower-6.jpg",
          "caption": "exterior - fairy ring"
        },
        {
          "src": "assets/uploads/1777415090776-exterior-wizards-tower-7.jpg",
          "caption": "exterior - south west"
        },
        {
          "src": "assets/uploads/1777415092189-exterior-wizards-tower-8.jpg",
          "caption": "exterior - front door"
        },
        {
          "src": "assets/uploads/1777415093811-exterior-wizards-tower-9.jpg",
          "caption": "exterior - footbridge"
        },
        {
          "src": "assets/uploads/1777415096152-exterior-wizards-tower-2.jpg",
          "caption": "exterior - north west"
        },
        {
          "src": "assets/uploads/1777415097398-exterior-wizards-tower-3.jpg",
          "caption": "exterior - front view"
        },
        {
          "src": "assets/uploads/1777415098668-exterior-wizards-tower-4.jpg",
          "caption": "exterior - aerial view"
        }
      ]
    },
    {
      "id": "lumbridge-west-exterior",
      "name": "Lumbridge West exterior",
      "subtitle": "Building the chapel, houses, paths, flora, graveyard and bridge. Don't forget Bob's axes!",
      "location": "backlog",
      "region": "Misthalin",
      "category": "building",
      "progress": 0,
      "fanRequest": false,
      "estimatedTotalTime": 20,
      "estimatedTimeLeft": "20 hours",
      "what": "Quest not started!",
      "images": []
    },
    {
      "id": "agree-block-palette",
      "name": "Agree block palette",
      "subtitle": "Test out and agree palette for housing and landmarks across Misthalin.",
      "location": "backlog",
      "region": "Misthalin",
      "category": "other",
      "progress": 0,
      "fanRequest": false,
      "estimatedTotalTime": 1,
      "estimatedTimeLeft": "1 hour",
      "what": "Quest not yet started!",
      "images": [
        {
          "src": "assets/uploads/1777319296894-600px-wizards-tower.png",
          "caption": "Wizards tower"
        }
      ]
    },
    {
      "id": "download-supporting-mods",
      "name": "Download supporting mods",
      "subtitle": "Figure out exactly what we need to build this well. Adding WorldEdit + supporting packs (CUI).",
      "location": "done",
      "region": "Misthalin",
      "category": "other",
      "progress": 100,
      "fanRequest": false,
      "estimatedTotalTime": 6,
      "estimatedTimeLeft": "0 hours",
      "what": "25/04: Identified WorldEdit mod builds compatible with conquest reforged and trialled in sandbox by building a wizard’s tower POC.\n\n27/04: Investigated Ardacraft's modpacks - some good content including Conquest:Architects and Conquest:Hearthfire (as well as minor packs). We decided not to include Create at this stage. We will use native tree functionality. \n\nQuest Complete!",
      "images": [
        {
          "src": "assets/uploads/1777285250007-66bec20f-395f-4492-9810-0aff121e324e.jpg",
          "caption": "Wizard’s Tower Exterior POC"
        }
      ]
    },
    {
      "id": "identify-foundation-map",
      "name": "Identify foundation map",
      "subtitle": "Scout out different options for the foundation of Gielinor. Scan ProjectMC and forums for pre-designed terrain in WorldPainter.",
      "location": "done",
      "region": "Misthalin",
      "category": "landscape",
      "progress": 100,
      "fanRequest": false,
      "estimatedTotalTime": 5,
      "estimatedTimeLeft": "0 hours",
      "what": "26/04: We’ve had a look at a few options for maps and found some great contenders. Major thanks to Nosferatu8 for the excellent foundations of their map design - we will be building from this 👍\n\nQuest complete!",
      "images": [
        {
          "src": "assets/uploads/1777284936704-img-4787.png",
          "caption": "Wilderness"
        },
        {
          "src": "assets/uploads/1777285605171-27f51d27-a0c4-483f-a7f7-83c01a1c78a3.jpg",
          "caption": "Black Knights’ fortress"
        },
        {
          "src": "assets/uploads/1777415275308-white-wolf-mountain.jpg",
          "caption": "white wolf mountain"
        },
        {
          "src": "assets/uploads/1777415331854-fremennik-province-troll-county.jpg",
          "caption": "fremennik province + troll county"
        }
      ]
    },
    {
      "id": "varrock-square-and-rooftops",
      "name": "Varrock square and rooftops",
      "subtitle": "Banks, streets, roofs, walls, market stalls, and the first dense city. To break up into smaller tickets.",
      "location": "backlog",
      "region": "Misthalin",
      "category": "building",
      "progress": 0,
      "fanRequest": false,
      "estimatedTotalTime": 40,
      "estimatedTimeLeft": "40 hours",
      "what": "Not started.",
      "images": [
        {
          "src": "assets/img/varrock-rooftops.svg",
          "caption": "Current roof palette and street density test."
        }
      ]
    },
    {
      "id": "lumbridge-castle-build",
      "name": "Lumbridge Castle build",
      "subtitle": "Our first major build ticket! Foundations, castle walls, and castle design.",
      "location": "backlog",
      "region": "Misthalin",
      "category": "building",
      "progress": 0,
      "fanRequest": false,
      "estimatedTotalTime": 20,
      "estimatedTimeLeft": "20 hours",
      "what": "Quest not yet started!",
      "images": [
        {
          "src": "assets/img/lumbridge-courtyard.svg",
          "caption": "Completed castle-courtyard scale and path-width proof."
        }
      ]
    }
  ]
}
